captivate_ai_api/Captivate.py
captivate_ai_api/__init__.py
captivate_ai_api-0.6.3.dist-info/METADATA
captivate_ai_api-0.6.3.dist-info/WHEEL
captivate_ai_api-0.6.3.dist-info/top_level.txt
captivate_ai_api-0.6.3.dist-info/RECORD
