Metadata-Version: 2.4
Name: captivate-ai-api
Version: 0.6.3
Summary: An API for Captivate conversation and state management
Home-page: https://github.com/captivatechat/captivate-ai-api
Author: Lance Del Valle
Author-email: lance@captivatechat.com
License: MIT
Classifier: Programming Language :: Python :: 3
Classifier: License :: OSI Approved :: MIT License
Classifier: Operating System :: OS Independent
Requires-Python: >=3.6
Requires-Dist: pydantic>=2.5.0
Requires-Dist: httpx>=0.25.2
Dynamic: author
Dynamic: author-email
Dynamic: classifier
Dynamic: description
Dynamic: description-content-type
Dynamic: home-page
Dynamic: license
Dynamic: requires-dist
Dynamic: requires-python
Dynamic: summary
